django_filer_image/__init__.py
django_filer_image/admin.py
django_filer_image/apps.py
django_filer_image/convertor.py
django_filer_image/jinja2/filer_images/image.html.j2
django_filer_image/migrations/0001_initial.py
django_filer_image/migrations/__init__.py
django_filer_image/models.py
django_filer_image/settings.py
django_filer_image/tests.py
django_filer_image/views.py
django_filer_image-0.0.2.dist-info/WHEEL
django_filer_image-0.0.2.dist-info/METADATA
django_filer_image-0.0.2.dist-info/RECORD
