Metadata-Version: 2.1
Name: django-filer-image
Version: 0.0.2
Summary: 
Author: Дмитрий
Author-email: acrius@mail.ru
Requires-Python: >=3.5,<4.0
Classifier: Programming Language :: Python :: 3
Classifier: Programming Language :: Python :: 3.5
Classifier: Programming Language :: Python :: 3.6
Classifier: Programming Language :: Python :: 3.7
Requires-Dist: django (>=1.11,<3.0)
Requires-Dist: django-filer (>=1.5,<2.0)
Requires-Dist: funcy (>=1.13,<2.0)
Requires-Dist: pillow (>=6.1.0,<7.0.0)
